corrosiffpy-0.1.2.dist-info/METADATA
corrosiffpy-0.1.2.dist-info/WHEEL
corrosiffpy.libs/libgcc_s-5b5488a6.so.1
corrosiffpy/__init__.py
corrosiffpy/__init__.pyi
corrosiffpy/py.typed
corrosiffpy/corrosiffpy.cpython-311-arm-linux-musleabihf.so
corrosiffpy-0.1.2.dist-info/RECORD
