Metadata-Version: 2.4
Name: corrosiffpy
Version: 0.1.2
Classifier: Programming Language :: Python :: 3
Classifier: Programming Language :: Rust
Requires-Dist: numpy >=1.15
Requires-Dist: pytest ; extra == 'test'
Requires-Dist: dropbox ; extra == 'test'
Provides-Extra: test
Summary: A Python wrapper for the `Rust` `corrosiff` library
Author: Stephen Thornquist
Author-email: thornquist@rockefeller.edu
License: GPL-3.0-or-later
Requires-Python: >=3.9.0
